{
  "version": 4,
  "configurations": [
    {
      "name": "Windows-x64",
      "compilerPath": "C:/Program Files/Microsoft Visual Studio/2022/Community/VC/Tools/MSVC/14.44.35207/bin/HostX64/x64/cl.exe",
      "cStandard": "c11",
      "includePath": [
        "${workspaceFolder}/Source"
      ],
      "defines": [
        "PNSLR_IMPLEMENTATION",
        "PNSLR_WINDOWS=1",
        "PNSLR_X64=1"
      ],
      "compilerArgs": [
        "/Brepro",
        "/nologo",
        "/std:c11",
        "/Wall",
        "/WX",
        "/wd4100",
        "/wd5045",
        "/wd4324",
        "/wd4820"
      ]
    },
    {
      "name": "Linux-x64",
      "compilerPath": "C:/Software/linux-cross-compiler/v19-clang-11.0.1-centos7/x86_64-unknown-linux-gnu/bin/clang.exe",
      "cStandard": "c11",
      "includePath": [
        "${workspaceFolder}/Source",
        "C:/Software/linux-cross-compiler/v19-clang-11.0.1-centos7/x86_64-unknown-linux-gnu/usr/include"
      ],
      "defines": [
        "PNSLR_IMPLEMENTATION",
        "PNSLR_LINUX=1",
        "PNSLR_X64=1"
      ],
      "compilerArgs": [
        "-std=c11",
        "-Wall",
        "-Wextra",
        "-Wshadow",
        "-Wconversion",
        "-Wsign-conversion",
        "-Wdouble-promotion",
        "-Wfloat-equal",
        "-Wundef",
        "-Wswitch-enum",
        "-Wstrict-prototypes",
        "-Werror",
        "-Wno-unused-parameter",
        "--sysroot=C:\\Software\\linux-cross-compiler\\v19-clang-11.0.1-centos7\\x86_64-unknown-linux-gnu\\",
        "--target=x86_64-unknown-linux-gnu"
      ]
    },
    {
      "name": "Linux-ARM64",
      "compilerPath": "C:/Software/linux-cross-compiler/v19-clang-11.0.1-centos7/aarch64-unknown-linux-gnueabi/bin/clang.exe",
      "cStandard": "c11",
      "includePath": [
        "${workspaceFolder}/Source",
        "C:/Software/linux-cross-compiler/v19-clang-11.0.1-centos7/aarch64-unknown-linux-gnueabi/usr/include"
      ],
      "defines": [
        "PNSLR_IMPLEMENTATION",
        "PNSLR_LINUX=1",
        "PNSLR_ARM64=1"
      ],
      "compilerArgs": [
        "-std=c11",
        "-Wall",
        "-Wextra",
        "-Wshadow",
        "-Wconversion",
        "-Wsign-conversion",
        "-Wdouble-promotion",
        "-Wfloat-equal",
        "-Wundef",
        "-Wswitch-enum",
        "-Wstrict-prototypes",
        "-Werror",
        "-Wno-unused-parameter",
        "--sysroot=C:\\Software\\linux-cross-compiler\\v19-clang-11.0.1-centos7\\aarch64-unknown-linux-gnueabi\\",
        "--target=aarch64-unknown-linux-gnueabi"
      ]
    },
    {
      "name": "Android-ARM64",
      "compilerPath": "C:/Users/HeroHiralal/AppData/Local/Android/Sdk/ndk/29.0.13113456/toolchains/llvm/prebuilt/windows-x86_64/bin/clang.exe",
      "cStandard": "c11",
      "includePath": [
        "${workspaceFolder}/Source",
        "C:/Users/HeroHiralal/AppData/Local/Android/Sdk/ndk/29.0.13113456/toolchains/llvm/prebuilt/windows-x86_64/sysroot/usr/include"
      ],
      "defines": [
        "PNSLR_IMPLEMENTATION",
        "PNSLR_ANDROID=1",
        "PNSLR_ARM64=1"
      ],
      "compilerArgs": [
        "-std=c11",
        "-Wall",
        "-Wextra",
        "-Wshadow",
        "-Wconversion",
        "-Wsign-conversion",
        "-Wdouble-promotion",
        "-Wfloat-equal",
        "-Wundef",
        "-Wswitch-enum",
        "-Wstrict-prototypes",
        "-Werror",
        "-Wno-unused-parameter",
        "--sysroot=C:\\Users\\HeroHiralal\\AppData\\Local\\Android\\Sdk\\ndk\\29.0.13113456\\toolchains\\llvm\\prebuilt\\windows-x86_64\\sysroot\\",
        "--target=aarch64-linux-android28"
      ]
    }
  ]
}